[
    {
        "id":"dem-02",
        "name":"CTD 22",
        "numero":"03 22 00 00",
        "valeur":"CTD 22 (03 22 00 00)"
    },
    {
        "id":"dem-03",
        "name":"CTD 29",
        "numero":"03 29 00 00",
        "valeur":"CTD 29 (03 29 00 00)"
    },
    {
        "id":"dem-04",
        "name":"CTD 35",
        "numero":"03 35 00 00",
        "valeur":"CTD 35 (03 35 00 00)"
    },
    {
        "id":"dem-05",
        "name":"CTD 44",
        "numero":"03 44 00 00",
        "valeur":"CTD 44 (03 44 00 00)"
    },
    {
        "id":"dem-06",
        "name":"CTD 49",
        "numero":"03 49 00 00",
        "valeur":"CTD 49 (03 49 00 00)"
    },
    {
        "id":"dem-07",
        "name":"CTD 53",
        "numero":"03 53 00 00",
        "valeur":"CTD 53 (03 53 00 00)"
    },
    {
        "id":"dem-08",
        "name":"CTD 56",
        "numero":"03 56 00 00",
        "valeur":"CTD 56 (03 56 00 00)"
    },
    {
        "id":"dem-09",
        "name":"CTD 72",
        "numero":"03 72 00 00",
        "valeur":"CTD 72 (03 72 00 00)"
    },
    {
        "id":"dem-10",
        "name":"CTD 85",
        "numero":"03 85 00 00",
        "valeur":"CTD 85 (03 85 00 00)"
    },
    {
        "id":"dem-11",
        "name":"CAP",
        "numero":"03 22 01 35",
        "valeur":"CAP TREBEURDEN (03 22 01 35)"
    },
    {
        "id":"dem-12",
        "name":"CIP GLENANS",
        "numero":"03 29 00 07",
        "valeur":"CIP GLENAN (03 29 007)"
    },
    {
        "id":"dem-13",
        "name":"CAMARET",
        "numero":"03 29 01 41",
        "valeur":"CAMARET (03 29 01 41)"
    },
    {
        "id":"dem-14",
        "name":"SUBEVASION",
        "numero":"03 85 023 C",
        "valeur":"SUBEVASION (03 85 023 C)"
    },
    {
        "id":"dem-15",
        "name":"MAITAI",
        "numero":"03 49 055 C",
        "valeur":"MAITAI (03 49 055 C)"
    },
    {
        "id":"dem-01",
        "name":"CTR",
        "numero":"03 00 00 00",
        "valeur":"CTR"
    }
]